sqlparser.cp36-win_amd64.pdb
sqlparser.cp36-win_amd64.pyd
python_sqlparser-1.2.dist-info/LICENSE
python_sqlparser-1.2.dist-info/METADATA
python_sqlparser-1.2.dist-info/WHEEL
python_sqlparser-1.2.dist-info/top_level.txt
python_sqlparser-1.2.dist-info/RECORD
