Metadata-Version: 2.1
Name: python-sqlparser
Version: 1.2
Summary: A package for parsing SQL queries
Home-page: https://github.com/546133753/python-sqlparser
Author: Timo Djürken
License: GPL
Platform: UNKNOWN
